efb_telegram_master/__init__.py
efb_telegram_master/__version__.py
efb_telegram_master/bot_manager.py
efb_telegram_master/chat.py
efb_telegram_master/chat_binding.py
efb_telegram_master/chat_destination_cache.py
efb_telegram_master/chat_object_cache.py
efb_telegram_master/commands.py
efb_telegram_master/constants.py
efb_telegram_master/db.py
efb_telegram_master/locale_handler.py
efb_telegram_master/locale_mixin.py
efb_telegram_master/master_message.py
efb_telegram_master/message.py
efb_telegram_master/msg_type.py
efb_telegram_master/rpc_utils.py
efb_telegram_master/slave_message.py
efb_telegram_master/utils.py
efb_telegram_master/wizard.py
efb_telegram_master/locale/az_AZ/LC_MESSAGES/efb_telegram_master.mo
efb_telegram_master/locale/az_AZ/LC_MESSAGES/efb_telegram_master.po
efb_telegram_master/locale/en_US/LC_MESSAGES/efb_telegram_master.mo
efb_telegram_master/locale/en_US/LC_MESSAGES/efb_telegram_master.po
efb_telegram_master/locale/es_AR/LC_MESSAGES/efb_telegram_master.mo
efb_telegram_master/locale/es_AR/LC_MESSAGES/efb_telegram_master.po
efb_telegram_master/locale/es_VE/LC_MESSAGES/efb_telegram_master.mo
efb_telegram_master/locale/es_VE/LC_MESSAGES/efb_telegram_master.po
efb_telegram_master/locale/id_ID/LC_MESSAGES/efb_telegram_master.mo
efb_telegram_master/locale/id_ID/LC_MESSAGES/efb_telegram_master.po
efb_telegram_master/locale/it_IT/LC_MESSAGES/efb_telegram_master.mo
efb_telegram_master/locale/it_IT/LC_MESSAGES/efb_telegram_master.po
efb_telegram_master/locale/ja_JP/LC_MESSAGES/efb_telegram_master.mo
efb_telegram_master/locale/ja_JP/LC_MESSAGES/efb_telegram_master.po
efb_telegram_master/locale/ms_MY/LC_MESSAGES/efb_telegram_master.mo
efb_telegram_master/locale/ms_MY/LC_MESSAGES/efb_telegram_master.po
efb_telegram_master/locale/ro_RO/LC_MESSAGES/efb_telegram_master.mo
efb_telegram_master/locale/ro_RO/LC_MESSAGES/efb_telegram_master.po
efb_telegram_master/locale/tr_TR/LC_MESSAGES/efb_telegram_master.mo
efb_telegram_master-2.3.1.dist-info/AUTHORS
efb_telegram_master-2.3.1.dist-info/LICENSE.md
efb_telegram_master-2.3.1.dist-info/METADATA
efb_telegram_master-2.3.1.dist-info/WHEEL
efb_telegram_master-2.3.1.dist-info/entry_points.txt
efb_telegram_master-2.3.1.dist-info/top_level.txt
efb_telegram_master-2.3.1.dist-info/RECORD
