Metadata-Version: 2.1
Name: efb-telegram-master
Version: 2.3.1
Summary: Telegram Master Channel for EH Forwarder Bot, based on Telegram Bot API.
Home-page: https://etm.1a23.studio
Author: Eana Hufwe
Author-email: ilove@1a23.com
License: AGPLv3+
Keywords: ehforwarderbot,EH Forwarder Bot,EH Forwarder Bot Master Channel,Telegram,Telegram Bot,chatbot
Platform: UNKNOWN
Classifier: Development Status :: 4 - Beta
Classifier: License :: OSI Approved :: GNU Affero General Public License v3 or later (AGPLv3+)
Classifier: Intended Audience :: Developers
Classifier: Intended Audience :: End Users/Desktop
Classifier: Programming Language :: Python :: 3 :: Only
Classifier: Programming Language :: Python :: 3.6
Classifier: Programming Language :: Python :: 3.7
Classifier: Topic :: Communications :: Chat
Classifier: Topic :: Utilities
Requires-Python: >=3.6
Requires-Dist: ehforwarderbot (>=2.0.0)
Requires-Dist: python-telegram-bot (~=13.11)
Requires-Dist: python-magic
Requires-Dist: ffmpeg-python
Requires-Dist: peewee
Requires-Dist: requests
Requires-Dist: pydub
Requires-Dist: ruamel.yaml
Requires-Dist: pillow
Requires-Dist: language-tags
Requires-Dist: retrying
Requires-Dist: bullet (>=2.2.0)
Requires-Dist: cjkwrap
Requires-Dist: humanize
Requires-Dist: typing-extensions (>=3.7.4.1)
Provides-Extra: tests
Requires-Dist: pytest ; extra == 'tests'
Requires-Dist: telethon ; extra == 'tests'
Requires-Dist: cryptg ; extra == 'tests'
Requires-Dist: pytest-dotenv ; extra == 'tests'
Requires-Dist: flaky ; extra == 'tests'
Requires-Dist: pytest-asyncio ; extra == 'tests'
Requires-Dist: mypy (>=0.910) ; extra == 'tests'
Requires-Dist: pytest-html ; extra == 'tests'
Requires-Dist: doit ; extra == 'tests'
Requires-Dist: PySocks ; extra == 'tests'
Requires-Dist: coverage ; extra == 'tests'
Requires-Dist: sphinx ; extra == 'tests'
Provides-Extra: tgs
Requires-Dist: lottie ; extra == 'tgs'
Requires-Dist: cairosvg ; extra == 'tgs'
